aixblock_ml/__init__.py
aixblock_ml/api.py
aixblock_ml/default_configs/Dockerfile
aixblock_ml/default_configs/README.md
aixblock_ml/default_configs/_wsgi.py
aixblock_ml/default_configs/_wsgi.py.tmpl
aixblock_ml/default_configs/docker-compose.yml
aixblock_ml/default_configs/model.py
aixblock_ml/default_configs/requirements.txt
aixblock_ml/exceptions.py
aixblock_ml/helpers.py
aixblock_ml/huggingface_configs/Dockerfile
aixblock_ml/huggingface_configs/README.md
aixblock_ml/huggingface_configs/_wsgi.py
aixblock_ml/huggingface_configs/docker-compose.yml
aixblock_ml/huggingface_configs/model.py
aixblock_ml/huggingface_configs/requirements-base.txt
aixblock_ml/huggingface_configs/requirements-test.txt
aixblock_ml/huggingface_configs/requirements.txt
aixblock_ml/model.py
aixblock_ml/server.py
aixblock_ml/templates/preview.html
aixblock_ml/utils.py
aixblock_ml-0.2.2.dist-info/METADATA
aixblock_ml-0.2.2.dist-info/WHEEL
aixblock_ml-0.2.2.dist-info/entry_points.txt
aixblock_ml-0.2.2.dist-info/RECORD
