Metadata-Version: 2.1
Name: aixblock_ml
Version: 0.2.2
Summary: 
Author: TonyShark
Author-email: quoi@wow-ai.com
Requires-Python: >=3.9,<4.0
Classifier: Programming Language :: Python :: 3
Classifier: Programming Language :: Python :: 3.9
Classifier: Programming Language :: Python :: 3.10
Classifier: Programming Language :: Python :: 3.11
